{
  "family": "strapi-task-siya",
  "networkMode": "awsvpc",
  "executionRoleArn": "arn:aws:iam::607700977843:role/strapi-ecs-task-exec-siya",
  "containerDefinitions": [
    {
      "name": "strapi",
      "image": "IMAGE_URI_PLACEHOLDER",
      "essential": true,
      "portMappings": [
        {
          "containerPort": 1337,
          "protocol": "tcp"
        }
      ],
      "logConfiguration": {
        "logDriver": "awslogs",
        "options": {
          "awslogs-group": "/ecs/strapi-siya",
          "awslogs-region": "us-east-2",
          "awslogs-stream-prefix": "ecs"
        }
      }
    }
  ],
  "requiresCompatibilities": ["FARGATE"],
  "cpu": "512",
  "memory": "1024"
}

